README.txt
setup.py
src/mekk/__init__.py
src/mekk.xmind.egg-info/PKG-INFO
src/mekk.xmind.egg-info/SOURCES.txt
src/mekk.xmind.egg-info/dependency_links.txt
src/mekk.xmind.egg-info/namespace_packages.txt
src/mekk.xmind.egg-info/not-zip-safe
src/mekk.xmind.egg-info/requires.txt
src/mekk.xmind.egg-info/top_level.txt
src/mekk/xmind/__init__.py
src/mekk/xmind/document.py
src/mekk/xmind/id_gen.py
src/mekk/xmind/xmlutil.py