Metadata-Version: 1.0
Name: mekk.xmind
Version: 0.5.0
Summary: XMind data files reading and writing library.
Home-page: http://bitbucket.org/Mekk/mekk.xmind/
Author: Marcin Kasperski
Author-email: Marcin.Kasperski@mekk.waw.pl
License: Artistic
Keywords: xmind
Platform: UNKNOWN
Classifier: Programming Language :: Python
Classifier: Intended Audience :: Developers
Classifier: Topic :: Software Development :: Libraries :: Python Modules
Classifier: License :: OSI Approved :: Mozilla Public License 1.1 (MPL 1.1)
Classifier: License :: OSI Approved :: Artistic License
Classifier: Development Status :: 4 - Beta
Classifier: Intended Audience :: Developers
Classifier: Operating System :: OS Independent
